gai/asm/__init__.py
gai/asm/asm.py
gai/asm/base.py
gai/asm/constants.py
gai/asm/agents/__init__.py
gai/asm/agents/base.py
gai/asm/agents/chat_agent.py
gai/asm/agents/tool_use_agent.py
gai/asm/api/main.py
gai/asm/states/InitializeState.py
gai/asm/states/PureActionState.py
gai/asm/states/PurePredicateState.py
gai/asm/states/ReadToDoState.py
gai/asm/states/UpdateToDoState.py
gai/asm/states/__init__.py
gai/mcp/__init__.py
gai/mcp/client/__init__.py
gai/mcp/client/mcp_client.py
gai/mcp/servers/__init__.py
gai/mcp/servers/mcp_common.py
gai/mcp/servers/mcp_pseudo.py
gai/messages/__init__.py
gai/messages/dialogue.py
gai/messages/message_counter.py
gai/messages/message_helper.py
gai/messages/message_store.py
gai/messages/monologue.py
gai/messages/typing.py
gai/nodes/__init__.py
gai/nodes/agent_node.py
gai/nodes/user_node.py
gai/sessions/__init__.py
gai/sessions/message_bus_base.py
gai/sessions/message_bus_local.py
gai/sessions/session_manager.py
gai/sessions/operations/chat.py
gai/sessions/operations/handshake.py
gai/sessions/operations/orchestrator.py
gai_sdk-1.0.251.dist-info/METADATA
gai_sdk-1.0.251.dist-info/WHEEL
gai_sdk-1.0.251.dist-info/licenses/LICENSE
gai_sdk-1.0.251.dist-info/RECORD
