Metadata-Version: 2.4
Name: gai-sdk
Version: 1.0.251
Summary: Refer to https://kakkoii1337.github.io/gai for more information
Author-email: kakkoii1337 <kakkoii1337@gmail.com>
License-File: LICENSE
Classifier: Development Status :: 3 - Alpha
Classifier: Intended Audience :: Developers
Classifier: Intended Audience :: Science/Research
Classifier: License :: OSI Approved :: MIT License
Classifier: Operating System :: OS Independent
Classifier: Programming Language :: Python :: 3.10
Classifier: Topic :: Scientific/Engineering :: Artificial Intelligence
Classifier: Topic :: Software Development
Classifier: Topic :: Software Development :: Libraries :: Python Modules
Requires-Python: >=3.10
Requires-Dist: gai-lib>=0.181.11
Requires-Dist: gai-llm>=0.1.4
Requires-Dist: mcp[cli]>=1.8.1
Requires-Dist: pillow>=11.3.0
Requires-Dist: transitions==0.9.2
Provides-Extra: dev
Requires-Dist: gai-lib[dev]; extra == 'dev'
